rmind_yandex_smart_home/__init__.py
rmind_yandex_smart_home/engine.py
rmind_yandex_smart_home/rootCA.crt
rmind_yandex_smart_home/yandex/__init__.py
rmind_yandex_smart_home/yandex/capability.py
rmind_yandex_smart_home/yandex/database.py
rmind_yandex_smart_home/yandex/device.py
rmind_yandex_smart_home/yandex/iam.py
rmind_yandex_smart_home/yandex/mqtt.py
rmind_yandex_smart_home/yandex/tools.py
rmind_yandex_smart_home-0.1.8.dist-info/METADATA
rmind_yandex_smart_home-0.1.8.dist-info/WHEEL
rmind_yandex_smart_home-0.1.8.dist-info/licenses/LICENSE
rmind_yandex_smart_home-0.1.8.dist-info/RECORD
