Metadata-Version: 2.4
Name: rmind_yandex_smart_home
Version: 0.1.8
Summary: Yandex smart home cloud function engine
Project-URL: Homepage, https://gitverse.ru/rmind.dev/rmind-alice-yandex-cloud-library
Project-URL: Issues, https://gitverse.ru/rmind.dev/rmind-alice-yandex-cloud-library/tasktracker
Author-email: "rMind.Dev" <rmind.dev@yandex.ru>, Korhog <grafinfector@hotmail.com>
License-File: LICENSE
Classifier: License :: OSI Approved :: MIT License
Classifier: Operating System :: OS Independent
Classifier: Programming Language :: Python :: 3
Requires-Python: >=3.10
Requires-Dist: paho-mqtt==1.6.1
Requires-Dist: requests
Requires-Dist: yandexcloud
Requires-Dist: ydb
